mmt_multipole_inversion/__about__.py
mmt_multipole_inversion/__init__.py
mmt_multipole_inversion/magnetic_sample.py
mmt_multipole_inversion/magnetic_sample_modules/__init__.py
mmt_multipole_inversion/magnetic_sample_modules/maxwell_cartesian_polynomials.py
mmt_multipole_inversion/magnetic_sample_modules/spherical_harmonics_basis.py
mmt_multipole_inversion/multipole_field/__init__.py
mmt_multipole_inversion/multipole_field/multipole_field_MCP.py
mmt_multipole_inversion/multipole_field/multipole_field_SHB.py
mmt_multipole_inversion/multipole_inversion.py
mmt_multipole_inversion/plot_tools.py
mmt_multipole_inversion/susceptibility_modules/__init__.py
mmt_multipole_inversion/susceptibility_modules/cartesian_spherical_harmonics.py
mmt_multipole_inversion/susceptibility_modules/cuda/__init__.py
mmt_multipole_inversion/susceptibility_modules/cuda/cudalib.pyx
mmt_multipole_inversion/susceptibility_modules/cuda/spherical_harmonics_basis.cu
mmt_multipole_inversion/susceptibility_modules/cuda/spherical_harmonics_basis.cuh
mmt_multipole_inversion/susceptibility_modules/maxwell_cartesian_polynomials.py
mmt_multipole_inversion/susceptibility_modules/spherical_harmonics_basis.py
mmt_multipole_inversion-1.0.dist-info/LICENSE
mmt_multipole_inversion-1.0.dist-info/WHEEL
mmt_multipole_inversion-1.0.dist-info/METADATA
mmt_multipole_inversion-1.0.dist-info/RECORD
