Metadata-Version: 2.1
Name: mmt-multipole-inversion
Version: 1.0
Summary: Library to generate scan grid measurements from multipole sources and perform numerical inversions
License: MIT
Author: D. Cortés-Ortuño
Author-email: d.i.cortes@uu.nl
Requires-Python: >=3.8,<3.11
Classifier: License :: OSI Approved :: MIT License
Classifier: Programming Language :: Python :: 3
Classifier: Programming Language :: Python :: 3.10
Classifier: Programming Language :: Python :: 3.8
Classifier: Programming Language :: Python :: 3.9
Requires-Dist: Cython (>=0.29.30,<0.30.0)
Requires-Dist: matplotlib (>=3.2,<4.0)
Requires-Dist: numba (>=0.55.2)
Requires-Dist: numpy (>=1.21,<1.23)
Requires-Dist: scipy (>=1.7.0,<2.0.0)
